json_toolkit.py
requests_toolkit.py
toolkit.py
json/requests_toolkit.py
requests_toolkit/json_tools.py
requests_toolkit-0.0.4.dist-info/LICENSE.txt
requests_toolkit-0.0.4.dist-info/METADATA
requests_toolkit-0.0.4.dist-info/WHEEL
requests_toolkit-0.0.4.dist-info/top_level.txt
requests_toolkit-0.0.4.dist-info/RECORD
