Metadata-Version: 2.1
Name: requests-toolkit
Version: 0.0.4
Summary: Decorators and other tools for handling common patterns with the python requests module.
Home-page: https://github.com/benjaminCallaghan/requests_toolkit
Author: benjaminCallaghan
Author-email: benjamin.r.callaghan@gmail.com
License: UNKNOWN
Platform: UNKNOWN
Classifier: Programming Language :: Python :: 3
Classifier: Programming Language :: Python :: 3.6
Classifier: Programming Language :: Python :: 3.7
Classifier: Programming Language :: Python :: 3.8
Classifier: Programming Language :: Python :: 3.9
Classifier: License :: OSI Approved :: GNU General Public License v3 or later (GPLv3+)
Classifier: Operating System :: OS Independent
Requires-Dist: requests (~=2.26.0)
Provides-Extra: dev
Requires-Dist: pytest (>=6.2.4) ; extra == 'dev'
